MANIFEST.in
setup.cfg
setup.py
d1_gazetteer/__init__.py
d1_gazetteer/manage.py
d1_gazetteer/settings.py
d1_gazetteer/urls.py
d1_gazetteer/wsgi.py
d1_gazetteer/service/__init__.py
d1_gazetteer/service/models.py
d1_gazetteer/service/views.py
dataone.gazetteer.egg-info/PKG-INFO
dataone.gazetteer.egg-info/SOURCES.txt
dataone.gazetteer.egg-info/dependency_links.txt
dataone.gazetteer.egg-info/top_level.txt