Metadata-Version: 1.0
Name: dataone.gazetteer
Version: 1.0.2
Summary: A Gazetteer service for DataONE
Home-page: http://dataone.org
Author: DataONE Project
Author-email: developers@dataone.org
License: Apache License, Version 2.0
Platform: UNKNOWN
